outpost24hiablib/__init__.py
outpost24hiablib/outpost24exceptions.py
outpost24hiablib/outpost24hiablib.py
outpost24hiablib/entities/__init__.py
outpost24hiablib/entities/scanner.py
outpost24hiablib/entities/target.py
outpost24hiablib/entities/targetgroup.py
outpost24hiablib/entities/user.py
outpost24hiablib/entities/usergroup.py
outpost24hiablib/tools/__init__.py
outpost24hiablib/tools/xmltools.py
outpost24hiablib-1.0.10.data/data/.VERSION
outpost24hiablib-1.0.10.data/data/AUTHORS.rst
outpost24hiablib-1.0.10.data/data/CONTRIBUTING.rst
outpost24hiablib-1.0.10.data/data/HISTORY.rst
outpost24hiablib-1.0.10.data/data/LICENSE
outpost24hiablib-1.0.10.data/data/Pipfile
outpost24hiablib-1.0.10.data/data/README.rst
outpost24hiablib-1.0.10.data/data/USAGE.rst
outpost24hiablib-1.0.10.data/data/dev-requirements.txt
outpost24hiablib-1.0.10.data/data/requirements.txt
outpost24hiablib-1.0.10.dist-info/AUTHORS.rst
outpost24hiablib-1.0.10.dist-info/LICENSE
outpost24hiablib-1.0.10.dist-info/METADATA
outpost24hiablib-1.0.10.dist-info/WHEEL
outpost24hiablib-1.0.10.dist-info/entry_points.txt
outpost24hiablib-1.0.10.dist-info/top_level.txt
outpost24hiablib-1.0.10.dist-info/RECORD
