Metadata-Version: 2.1
Name: outpost24hiablib
Version: 1.0.10
Summary: Client for interacting with Outpost24 HIAB
Home-page: https://github.com/schubergphilis/outpost24hiablib
Author: Theodoor Scholte
Author-email: tscholte@schubergphilis.com
License: MIT
Keywords: outpost24 HIAB API XML python
Platform: UNKNOWN
Classifier: Development Status :: 1 - Planning
Classifier: Intended Audience :: Developers
Classifier: License :: OSI Approved :: MIT License
Classifier: Natural Language :: English
Classifier: Programming Language :: Python :: 3.7
Requires-Dist: requests (>=2.22.0)
